coopgame/IGameTemplate.py
coopgame/__init__.py
coopgame/camera.py
coopgame/chunkRendering.py
coopgame/coordinateConverter.py
coopgame/enums.py
coopgame/gameTemplate.py
coopgame/gameTimeTracker.py
coopgame/handleKeyPressedArgs.py
coopgame/logger.py
coopgame/monitoredClassLogger.py
coopgame/pyZoneHandler.py
coopgame/pyfonts.py
coopgame/pygame_k_constant_names.py
coopgame/pygamehelpers.py
coopgame/pygbutton.py
coopgame/runtime_config.py
coopgame/scrollHandler.py
coopgame/snapState.py
coopgame/surfaceManager.py
coopgame/tilemap.py
coopgame/characterDevelopment/__init__.py
coopgame/characterDevelopment/character.py
coopgame/characterDevelopment/community.py
coopgame/characterDevelopment/manifests.py
coopgame/characterDevelopment/race_factory.py
coopgame/characterDevelopment/stat_modifier_manifest.py
coopgame/characterDevelopment/stats.py
coopgame/characterDevelopment/behaviorExtensions/__init__.py
coopgame/characterDevelopment/behaviorExtensions/casting.py
coopgame/characterDevelopment/behaviorExtensions/dual.py
coopgame/characterDevelopment/behaviorExtensions/experience.py
coopgame/characterDevelopment/behaviorExtensions/hp.py
coopgame/characterDevelopment/behaviorExtensions/skills.py
coopgame/characterDevelopment/behaviorExtensions/traits.py
coopgame/collision/__init__.py
coopgame/collision/collider.py
coopgame/grids_graphs/__init__.py
coopgame/grids_graphs/draw_graph_utils.py
coopgame/grids_graphs/draw_grid_utils.py
coopgame/grids_graphs/pygraphhandler.py
coopgame/grids_graphs/pygridgraphHandler.py
coopgame/grids_graphs/pygridhandler.py
coopgame/harfang/__init__.py
coopgame/harfang/harfangColorConverter.py
coopgame/harfang/harfangGameTemplate.py
coopgame/harfang/harfangPrimitives.py
coopgame/label_drawing/__init__.py
coopgame/label_drawing/label_drawing_utils.py
coopgame/label_drawing/pyLabel.py
coopgame/linedrawing/__init__.py
coopgame/linedrawing/curve_draw_utils.py
coopgame/linedrawing/line_draw_utils.py
coopgame/linedrawing/pyCurveHandler.py
coopgame-1.18.dist-info/LICENSE
coopgame-1.18.dist-info/METADATA
coopgame-1.18.dist-info/WHEEL
coopgame-1.18.dist-info/top_level.txt
coopgame-1.18.dist-info/RECORD
